bin/display_information.py
bin/start-wifi-connect.py
firmware/atom_s3_i2c_display/extra_script.py
firmware/atom_s3_i2c_display/upload_script.py
firmware/esp_now_pairing/extra_script.py
riberry/__init__.py
riberry/embedding_cache.py
riberry/esp_now_pairing.py
riberry/filecheck_utils.py
riberry/firmware_update.py
riberry/git_utils.py
riberry/marker_manager.py
riberry/mode.py
riberry/mode_type.py
riberry/motion_manager.py
riberry/network.py
riberry/select_list.py
riberry/teaching_interface.py
riberry/teaching_manager.py
riberry/wifi_connect_utils.py
riberry/apps/__init__.py
riberry/apps/riberry_analyze_core_dump.py
riberry/apps/riberry_update_firmware.py
riberry/battery/__init__.py
riberry/battery/common.py
riberry/battery/mp2760.py
riberry/battery/pisugar.py
riberry/com/__init__.py
riberry/com/base.py
riberry/com/i2c_base.py
riberry/com/uart_base.py
riberry/platformio/__init__.py
riberry/platformio/core_dump.py
riberry/platformio/device_to_mcu.py
riberry/platformio/toolchain.py
riberry_robot-0.1.3.dist-info/licenses/LICENSE
ros/riberry_startup/node_scripts/button_action_manager.py
ros/riberry_startup/node_scripts/change_atom_echo_led_color.py
ros/riberry_startup/node_scripts/change_systemd_rosmaster.py
ros/riberry_startup/node_scripts/display_battery_graph_mode.py
ros/riberry_startup/node_scripts/display_odom_mode.py
ros/riberry_startup/node_scripts/imu_filter.py
ros/riberry_startup/node_scripts/imu_orientation.py
ros/riberry_startup/node_scripts/keyword_extraction.py
ros/riberry_startup/node_scripts/keyword_to_action.py
ros/riberry_startup/node_scripts/mux_selector.py
ros/riberry_startup/node_scripts/package_list_service.py
ros/riberry_startup/node_scripts/pressure_control_mode.py
ros/riberry_startup/node_scripts/pump_switcher.py
ros/riberry_startup/node_scripts/servo_control_mode.py
ros/riberry_startup/node_scripts/set_mode.py
ros/riberry_startup/node_scripts/speak_to_light.py
ros/riberry_startup/node_scripts/speech_to_text.py
ros/riberry_startup/node_scripts/speech_to_text_mode.py
riberry_robot-0.1.3.dist-info/METADATA
riberry_robot-0.1.3.dist-info/WHEEL
riberry_robot-0.1.3.dist-info/entry_points.txt
riberry_robot-0.1.3.dist-info/top_level.txt
riberry_robot-0.1.3.dist-info/RECORD
