Metadata-Version: 2.4
Name: riberry-robot
Version: 0.1.3
Summary: Riberry: Robot Intelligent Binary Enhancement Resource Revolutionary Yield
Author-email: Iori Yanokura <yanokura@jsk.imi.i.u-tokyo.ac.jp>, Naoya Yamaguchi <yamaguchi@jsk.imi.i.u-tokyo.ac.jp>, Aoi Nakane <nakane@jsk.imi.i.u-tokyo.ac.jp>
License: Copyright (c) 2024 Iori Yanokura.
Project-URL: Homepage, https://github.com/iory/riberry
Project-URL: Repository, https://github.com/iory/riberry
Keywords: riberry,robotics,automation,robot module
Classifier: Programming Language :: Python :: 3
Classifier: License :: OSI Approved :: MIT License
Classifier: Operating System :: OS Independent
License-File: LICENSE
Requires-Dist: Adafruit-Blinka
Requires-Dist: adafruit-circuitpython-mprls
Requires-Dist: colorama
Requires-Dist: GitPython
Requires-Dist: filelock
Requires-Dist: i2c-for-esp32
Requires-Dist: platformio
Requires-Dist: pybsc
Requires-Dist: pyserialtransfer==2.1.6
Requires-Dist: smbus2
Dynamic: license-file
